creatio_odata_api/__init__.py
creatio_odata_api/api.py
creatio_odata_api/logs.py
creatio_odata_api/py.typed
creatio_odata_api/utils.py
creatio_odata_api-1.1.1.dist-info/LICENSE
creatio_odata_api-1.1.1.dist-info/METADATA
creatio_odata_api-1.1.1.dist-info/WHEEL
creatio_odata_api-1.1.1.dist-info/RECORD
