Metadata-Version: 2.1
Name: creatio-odata-api
Version: 1.1.1
Summary: Python client for Creatio OData API
Home-page: https://github.com/yisuschrist/creatio-odata-api
License: GPL-3.0-only
Author: Alejandro González Momblán
Author-email: alejandro.gonzalez.momblan@evoluciona.es
Requires-Python: >=3.12,<4.0
Classifier: License :: OSI Approved :: GNU General Public License v3 (GPLv3)
Classifier: Programming Language :: Python :: 3
Classifier: Programming Language :: Python :: 3.12
Requires-Dist: python-dotenv (>=1.0.1,<2.0.0)
Requires-Dist: requests (>=2.31.0,<3.0.0)
Requires-Dist: requests-cache (>=1.1.1,<2.0.0)
Requires-Dist: requests-pprint (>=1.0.0,<2.0.0)
Requires-Dist: rich (>=13.7.0,<14.0.0)
Project-URL: Repository, https://github.com/yisuschrist/creatio-odata-api
